desmoscl/__init__.py
desmoscl/eqntest.py
desmoscl/flowchart.py
desmoscl/ineqtest.py
desmoscl/rxnbal.py
desmoscl/tableread.py
desmoscl-1.0.6.dist-info/METADATA
desmoscl-1.0.6.dist-info/WHEEL
desmoscl-1.0.6.dist-info/entry_points.txt
desmoscl-1.0.6.dist-info/top_level.txt
desmoscl-1.0.6.dist-info/RECORD
