Metadata-Version: 2.4
Name: desmoscl
Version: 1.0.6
Summary: Python Tools for Programming Desmos/Amplify Computation Layer (CL), maintained by Ganesh Sriram
Author-email: Ganesh Sriram <gsriram@umd.edu>
Project-URL: Homepage, https://github.com/gsriramlab-umd
Project-URL: Issues, https://github.com/gsriramlab-umd
Keywords: desmos,amplify,cl,computation layer,classroom
Classifier: Programming Language :: Python :: 3
Classifier: Operating System :: OS Independent
Requires-Python: >=3.9
Provides-Extra: dev
Requires-Dist: pytest; extra == "dev"
Requires-Dist: build; extra == "dev"
Requires-Dist: twine; extra == "dev"
